[
    {
        "id": 1,
        "mentor":{
            "image": "https://www.shutterstock.com/image-photo/head-shot-portrait-close-smiling-250nw-1714666150.jpg",
            "name": "Rick Thomson"
        },
        "intern":{
            "image": "https://d2v5dzhdg4zhx3.cloudfront.net/web-assets/images/storypages/short/linkedin-profile-picture-maker/dummy_image/thumb/004.webp",
            "name": "Tina Rose"
        },
        "status": "In Progress",
        "startDate": "01/01/2023",
        "endDate": "07/01/2023",
        "action": "intern1@example.com"
    },
    {
        "id": 2,
        "mentor":{
            "image": "https://www.shutterstock.com/image-photo/head-shot-portrait-close-smiling-250nw-1714666150.jpg",
            "name": "Rick Thomson"
        },
        "intern":{
            "image": "https://d2v5dzhdg4zhx3.cloudfront.net/web-assets/images/storypages/short/linkedin-profile-picture-maker/dummy_image/thumb/004.webp",
            "name": "Tina Rose"
        },
        "status": "In Progress",
        "startDate": "01/01/2023",
        "endDate": "07/01/2023",
        "action": "intern1@example.com"
    },
    {
        "id": 3,
        "mentor":{
            "image": "https://www.shutterstock.com/image-photo/head-shot-portrait-close-smiling-250nw-1714666150.jpg",
            "name": "Rick Thomson"
        },
        "intern":{
            "image": "https://d2v5dzhdg4zhx3.cloudfront.net/web-assets/images/storypages/short/linkedin-profile-picture-maker/dummy_image/thumb/004.webp",
            "name": "Tina Rose"
        },
        "status": "In Progress",
        "startDate": "01/01/2023",
        "endDate": "07/01/2023",
        "action": "intern1@example.com"
    },
    {
        "id": 4,
        "mentor":{
            "image": "https://www.shutterstock.com/image-photo/head-shot-portrait-close-smiling-250nw-1714666150.jpg",
            "name": "Rick Thomson"
        },
        "intern":{
            "image": "https://d2v5dzhdg4zhx3.cloudfront.net/web-assets/images/storypages/short/linkedin-profile-picture-maker/dummy_image/thumb/004.webp",
            "name": "Tina Rose"
        },
        "status": "Done",
        "startDate": "01/01/2023",
        "endDate": "07/01/2023",
        "action": "intern1@example.com"
    },
    {
        "id": 5,
        "mentor":{
            "image": "https://www.shutterstock.com/image-photo/head-shot-portrait-close-smiling-250nw-1714666150.jpg",
            "name": "Rick Thomson"
        },
        "intern":{
            "image": "https://d2v5dzhdg4zhx3.cloudfront.net/web-assets/images/storypages/short/linkedin-profile-picture-maker/dummy_image/thumb/004.webp",
            "name": "Tina Rose"
        },
        "status": "Done",
        "startDate": "01/01/2023",
        "endDate": "07/01/2023",
        "action": "intern1@example.com"
    },
    {
        "id": 6,
        "mentor":{
            "image": "https://www.shutterstock.com/image-photo/head-shot-portrait-close-smiling-250nw-1714666150.jpg",
            "name": "Rick Thomson"
        },
        "intern":{
            "image": "https://d2v5dzhdg4zhx3.cloudfront.net/web-assets/images/storypages/short/linkedin-profile-picture-maker/dummy_image/thumb/004.webp",
            "name": "Tina Rose"
        },
        "status": "In Progress",
        "startDate": "01/01/2023",
        "endDate": "07/01/2023",
        "action": "intern1@example.com"
    },
    {
        "id": 7,
        "mentor":{
            "image": "https://www.shutterstock.com/image-photo/head-shot-portrait-close-smiling-250nw-1714666150.jpg",
            "name": "Rick Thomson"
        },
        "intern":{
            "image": "https://d2v5dzhdg4zhx3.cloudfront.net/web-assets/images/storypages/short/linkedin-profile-picture-maker/dummy_image/thumb/004.webp",
            "name": "Tina Rose"
        },
        "status": "In Progress",
        "startDate": "01/01/2023",
        "endDate": "07/01/2023",
        "action": "intern1@example.com"
    },
    {
        "id": 8,
        "mentor":{
            "image": "https://www.shutterstock.com/image-photo/head-shot-portrait-close-smiling-250nw-1714666150.jpg",
            "name": "Rick Thomson" 
        },
        "intern":{
            "image": "https://d2v5dzhdg4zhx3.cloudfront.net/web-assets/images/storypages/short/linkedin-profile-picture-maker/dummy_image/thumb/004.webp",
            "name": "Tina Rose"
        },
        "status": "In Progress",
        "startDate": "01/01/2023",
        "endDate": "07/01/2023",
        "action": "intern1@example.com"
    },
    {
        "id": 9,
        "mentor":{
            "image": "https://www.shutterstock.com/image-photo/head-shot-portrait-close-smiling-250nw-1714666150.jpg",
            "name": "Rick Thomson"
        },
        "intern":{
            "image": "https://d2v5dzhdg4zhx3.cloudfront.net/web-assets/images/storypages/short/linkedin-profile-picture-maker/dummy_image/thumb/004.webp",
            "name": "Tina Rose"
        },
        "status": "Done",
        "startDate": "01/01/2023",
        "endDate": "07/01/2023",
        "action": "intern1@example.com"
    },
    {
        "id": 10,
        "mentor":{
            "image": "https://www.shutterstock.com/image-photo/head-shot-portrait-close-smiling-250nw-1714666150.jpg",
            "name": "Rick Thomson"
        },
        "intern":{
            "image": "https://d2v5dzhdg4zhx3.cloudfront.net/web-assets/images/storypages/short/linkedin-profile-picture-maker/dummy_image/thumb/004.webp",
            "name": "Tina Rose"
        },
        "status": "Done",
        "startDate": "01/01/2023",
        "endDate": "07/01/2023",
        "action": "intern1@example.com"
    },
    {
        "id": 11,
        "mentor":{
            "image": "https://www.shutterstock.com/image-photo/head-shot-portrait-close-smiling-250nw-1714666150.jpg",
            "name": "Rick Thomson"
        },
        "intern":{
            "image": "https://d2v5dzhdg4zhx3.cloudfront.net/web-assets/images/storypages/short/linkedin-profile-picture-maker/dummy_image/thumb/004.webp",
            "name": "Tina Rose"
        },
        "status": "In Progress",
        "startDate": "01/01/2023",
        "endDate": "07/01/2023",
        "action": "intern1@example.com"
    },
    {
        "id": 12,
        "mentor":{
            "image": "https://www.shutterstock.com/image-photo/head-shot-portrait-close-smiling-250nw-1714666150.jpg",
            "name": "Rick Thomson"
        },
        "intern":{
            "image": "https://d2v5dzhdg4zhx3.cloudfront.net/web-assets/images/storypages/short/linkedin-profile-picture-maker/dummy_image/thumb/004.webp",
            "name": "Tina Rose"
        },
        "status": "In Progress",
        "startDate": "01/01/2023",
        "endDate": "07/01/2023",
        "action": "intern1@example.com"
    },
    {
        "id": 13,
        "mentor":{
            "image": "https://www.shutterstock.com/image-photo/head-shot-portrait-close-smiling-250nw-1714666150.jpg",
            "name": "Rick Thomson"
        },
        "intern":{
            "image": "https://d2v5dzhdg4zhx3.cloudfront.net/web-assets/images/storypages/short/linkedin-profile-picture-maker/dummy_image/thumb/004.webp",
            "name": "Tina Rose"
        },
        "status": "In Progress",
        "startDate": "01/01/2023",
        "endDate": "07/01/2023",
        "action": "intern1@example.com"
    },
    {
        "id": 14,
        "mentor":{
            "image": "https://www.shutterstock.com/image-photo/head-shot-portrait-close-smiling-250nw-1714666150.jpg",
            "name": "Rick Thomson"
        },
        "intern":{
            "image": "https://d2v5dzhdg4zhx3.cloudfront.net/web-assets/images/storypages/short/linkedin-profile-picture-maker/dummy_image/thumb/004.webp",
            "name": "Tina Rose"
        },
        "status": "Done",
        "startDate": "01/01/2023",
        "endDate": "07/01/2023",
        "action": "intern1@example.com"
    },
    {
        "id": 15,
        "mentor":{
            "image": "https://www.shutterstock.com/image-photo/head-shot-portrait-close-smiling-250nw-1714666150.jpg",
            "name": "Rick Thomson"
        },
        "intern":{
            "image": "https://d2v5dzhdg4zhx3.cloudfront.net/web-assets/images/storypages/short/linkedin-profile-picture-maker/dummy_image/thumb/004.webp",
            "name": "Tina Rose"
        },
        "status": "Done",
        "startDate": "01/01/2023",
        "endDate": "07/01/2023",
        "action": "intern1@example.com"
    }
    
]